pyasdl/__init__.py
pyasdl/asdl.py
pyasdl/grammar.py
pyasdl/parser.py
pyasdl/visitors.py
pyasdl/static/asdl.gram
pyasdl-22.1.23.dist-info/LICENSE.txt
pyasdl-22.1.23.dist-info/METADATA
pyasdl-22.1.23.dist-info/WHEEL
pyasdl-22.1.23.dist-info/top_level.txt
pyasdl-22.1.23.dist-info/RECORD
