Metadata-Version: 2.1
Name: pyasdl
Version: 22.1.23
Summary: ASDL Parser
Home-page: https://github.com/isidentical/pyasdl
Author: isidentical
Author-email: isidentical@gmail.com
License: MIT
Platform: UNKNOWN
Classifier: License :: OSI Approved :: MIT License
Classifier: Programming Language :: Python :: 3
Classifier: Programming Language :: Python :: 3 :: Only
Classifier: Programming Language :: Python :: 3.9
Classifier: Programming Language :: Python :: 3.10
Requires-Python: >=3.9
License-File: LICENSE.txt
Requires-Dist: pegen (==0.1.0)
